LICENSE
MANIFEST.in
README.md
requirements-test.txt
requirements.txt
setup.py
ubuntu_bug_triage/__init__.py
ubuntu_bug_triage/__main__.py
ubuntu_bug_triage/bug.py
ubuntu_bug_triage/test_bug.py
ubuntu_bug_triage/test_triage.py
ubuntu_bug_triage/test_view.py
ubuntu_bug_triage/triage.py
ubuntu_bug_triage/view.py
ubuntu_bug_triage.egg-info/PKG-INFO
ubuntu_bug_triage.egg-info/SOURCES.txt
ubuntu_bug_triage.egg-info/dependency_links.txt
ubuntu_bug_triage.egg-info/entry_points.txt
ubuntu_bug_triage.egg-info/requires.txt
ubuntu_bug_triage.egg-info/top_level.txt
ubuntu_bug_triage.egg-info/zip-safe