Metadata-Version: 2.1
Name: ubuntu-bug-triage
Version: 21.1
Summary: Recently updated Launchpad bugs for triage
Home-page: https://github.com/powersj/ubuntu-bug-triage
Author: Joshua Powers
Author-email: josh.powers@canonical.com
License: UNKNOWN
Download-URL: https://github.com/powersj/ubuntu-bug-triage/tarball/master
Keywords: ubuntu,launchpad,triage,bugs
Platform: UNKNOWN
Classifier: Development Status :: 5 - Production/Stable
Classifier: Environment :: Console
Classifier: Intended Audience :: Developers
Classifier: License :: OSI Approved :: GNU General Public License v3 (GPLv3)
Classifier: Natural Language :: English
Classifier: Operating System :: POSIX :: Linux
Classifier: Programming Language :: Python :: 3 :: Only
Classifier: Programming Language :: Python :: 3.6
Classifier: Programming Language :: Python :: 3.7
Classifier: Programming Language :: Python :: 3.8
Classifier: Topic :: Software Development :: Quality Assurance
Classifier: Topic :: Software Development :: Testing
Requires-Python: >=3.6
